[
      {
    "id": "movie_a6kgd5k11",
    "TieuDe": "MVG-144 ",
    "anh": "https://pics.dmm.co.jp/digital/video/mvg00144/mvg00144jp-17.jpg",
    "moTa": "",
    "loai": "movie",
    "Dang": ".m3u8",
    "boloc": [
      "Sự Sỉ Nhục AV",
      "Hay được chọn lọc"
    ],
    "ThuyetMinh": [],
    "LongTieng": [],
    "tap": [
      {
        "tapSo": null,
        "video": "https://faf8b60b.cold-winter-118.space/blah3/XEn0ezUAjwPK3UvwUqJFPdjlgExgjJxMWL7L_ASajRMAmg/qc/v.m3u8",
        "subtitle": "",
        "GioiThieuBatDau": "",
        "GioiThieuKetThuc": ""
      }
    ]
  },
      {
    "id": "movie_3dd6vct26",
    "TieuDe": "SW-331 .",
    "anh": "https://javmedia.s3.amazonaws.com/videos/1sw00331/sample_4.jpg",
    "moTa": "",
    "loai": "movie",
    "Dang": ".m3u8",
    "boloc": [
      "Không che",
      "Hay được chọn lọc"
    ],
    "ThuyetMinh": [],
    "LongTieng": [],
    "tap": [
      {
        "tapSo": null,
        "video": "https://fd957212.hot-desert-117.site/blah3/XEn0ezcAjwPK3UvwUqJFPNi2gUxq0Z9ZH+HI_ASajR0AmtNi/qb/v.m3u8",
        "subtitle": "",
        "GioiThieuBatDau": "",
        "GioiThieuKetThuc": ""
      }
    ]
  },
     {
    "id": "movie_r7u3g0v5g",
    "TieuDe": "BONY-157 ",
    "anh": "https://javmedia.s3.amazonaws.com/videos/bony00157/sample_17.jpg",
    "moTa": "",
    "loai": "movie",
    "Dang": ".m3u8",
    "boloc": [
      "Sự Sỉ Nhục AV",
      "Lệnh"
    ],
    "ThuyetMinh": [],
    "LongTieng": [],
    "tap": [
      {
        "tapSo": null,
        "video": "https://649c23a8.fresh-spring-119.store/blah3/XEn0ezAckFvTgxX3A7ZKZZv9jwd3jcJEWqnLuBCPgxcHz4E/qc/v.m3u8",
        "subtitle": "",
        "GioiThieuBatDau": "",
        "GioiThieuKetThuc": ""
      }
    ]
  },
   
     {
    "id": "movie_xpdrmk45u",
    "TieuDe": "EBOD-998 ",
    "anh": "https://www.pornjav.icu/contents/videos_screenshots/385000/385732/preview.jpg",
    "moTa": "",
    "loai": "movie",
    "Dang": ".m3u8",
    "boloc": [
      "Tổng Hợp",
      "Không che",
      "Hay được chọn lọc"
    ],
    "ThuyetMinh": [],
    "LongTieng": [],
    "tap": [
      {
        "tapSo": null,
        "video": "https://42ae690f.bright-light-107.store/blah3/XEn0ezMAjwPK3UvwUqJFMdi8m0xgg5xaCaKH_ASajRkKnIYyxw/qb/v.m3u8",
        "subtitle": "",
        "GioiThieuBatDau": "",
        "GioiThieuKetThuc": ""
      }
    ]
  },

     {
    "id": "movie_k3mxpur3e",
    "TieuDe": "MEYD-862 .",
    "anh": "https://javmedia.s3.amazonaws.com/videos/meyd00862/sample_2.jpg",
    "moTa": "",
    "loai": "movie",
    "Dang": ".m3u8",
    "boloc": [
      "Hay được chọn lọc"
    ],
    "ThuyetMinh": [],
    "LongTieng": [],
    "tap": [
      {
        "tapSo": null,
        "video": "https://3b72d1ab.wild-forest-115.space/blah3/XEn0ezYAjwPK3UvwUqJFYdi1h0xgxYREHb3f9gSajRwFz4Vh/qb/v.m3u8",
        "subtitle": "",
        "GioiThieuBatDau": "",
        "GioiThieuKetThuc": ""
      }
    ]
  },
 {
    "id": "movie_2z1njywdx",
    "TieuDe": "NSFS-413 ",
    "anh": "https://pics.dmm.co.jp/digital/video/nsfs00413/nsfs00413jp-5.jpg",
    "moTa": "",
    "loai": "movie",
    "Dang": ".m3u8",
    "boloc": [
      "Bị Cắm Sừng",
      "Hay được chọn lọc"
    ],
    "ThuyetMinh": [],
    "LongTieng": [],
    "tap": [
      {
        "tapSo": null,
        "video": "https://19e9ce43.white-cloud-103.space/blah3/XEn0ezcAjwPK3UvwUqJFMNi4gUwzz54IFenE_ASajRIGxw/qc/v.m3u8",
        "subtitle": "",
        "GioiThieuBatDau": "",
        "GioiThieuKetThuc": ""
      }
    ]
  },
  {
    "id": "movie_eo7sc06aw",
    "TieuDe": "SONE-954 ",
    "anh": "https://file.tkcdns.com/contents/videos_sources/356000/356367/screenshots/2.jpg",
    "moTa": "",
    "loai": "movie",
    "Dang": ".m3u8",
    "boloc": [
      "Sự Sỉ Nhục AV",
      "Hay được chọn lọc"
    ],
    "ThuyetMinh": [],
    "LongTieng": [],
    "tap": [
      {
        "tapSo": null,
        "video": "https://19e9ce43.cold-winter-118.space/blah3/XEn0ezAAjwPK3UvwUqJFKtiij0xgxZZOCKrI9gSajRkBzdZmxQ/qc/v.m3u8",
        "subtitle": "",
        "GioiThieuBatDau": "",
        "GioiThieuKetThuc": ""
      }
    ]
  }
]